README.md
setup.py
balls/__init__.py
balls/main.py
balls.egg-info/PKG-INFO
balls.egg-info/SOURCES.txt
balls.egg-info/dependency_links.txt
balls.egg-info/requires.txt
balls.egg-info/top_level.txt
balls.egg-info/zip-safe